encryption/__init__.py
outbox_encryption-1.1.6.dist-info/LICENSE.md
outbox_encryption-1.1.6.dist-info/METADATA
outbox_encryption-1.1.6.dist-info/WHEEL
outbox_encryption-1.1.6.dist-info/top_level.txt
outbox_encryption-1.1.6.dist-info/RECORD
