Metadata-Version: 2.1
Name: outbox-encryption
Version: 1.1.6
Summary: DJANGO OUTBOX ENCRYPTION
Home-page: https://github.com/PROJECT-OUTBOX/django_lib_outbox_encryption.git
Author-email: suratiwan03@gmail.com
Keywords: encrypt,decrypt,environment,django,settings
Classifier: License :: OSI Approved :: BSD License
Classifier: Intended Audience :: Developers
Classifier: Programming Language :: Python :: 3 :: Only
License-File: LICENSE.md
Requires-Dist: cryptography
Requires-Dist: python-decouple
